{
    "name": "Graveler",
    "base_stats": {
        "hp": 55,
        "attack": 95,
        "defense": 115,
        "speed": 35,
        "special_attack": 45,
        "special_defense": 45
    },
    "types": [
        "TYPE_ROCK",
        "TYPE_GROUND"
    ],
    "catch_rate": 120,
    "base_exp_reward": 134,
    "ev_yields": {
        "hp": 0,
        "attack": 0,
        "defense": 2,
        "speed": 0,
        "special_attack": 0,
        "special_defense": 0
    },
    "held_items": {
        "common": "ITEM_NONE",
        "rare": "ITEM_EVERSTONE"
    },
    "gender_ratio": "GENDER_RATIO_FEMALE_50",
    "hatch_cycles": 15,
    "base_friendship": 70,
    "exp_rate": "EXP_RATE_MEDIUM_SLOW",
    "egg_groups": [
        "EGG_GROUP_MINERAL",
        "EGG_GROUP_MINERAL"
    ],
    "abilities": [
        "ABILITY_ROCK_HEAD",
        "ABILITY_STURDY"
    ],
    "great_marsh_flee_rate": 0,
    "sprite": {
        "color": "MON_COLOR_BROWN",
        "flip_sprite": false
    },
    "learnset": {
        "tms": [
            "TM01",
            "TM06",
            "TM10",
            "TM11",
            "TM17",
            "TM21",
            "TM26",
            "TM27",
            "TM28",
            "TM31",
            "TM32",
            "TM35",
            "TM37",
            "TM38",
            "TM39",
            "TM42",
            "TM43",
            "TM44",
            "TM45",
            "TM56",
            "TM58",
            "TM64",
            "TM69",
            "TM71",
            "TM74",
            "TM76",
            "TM78",
            "TM80",
            "TM82",
            "TM83",
            "TM87",
            "TM90",
            "HM04",
            "HM06",
            "HM08"
        ],
        "level_up": {
            "1": [
                "MOVE_TACKLE",
                "MOVE_DEFENSE_CURL",
                "MOVE_MUD_SPORT",
                "MOVE_ROCK_POLISH"
            ],
            "4": "MOVE_MUD_SPORT",
            "8": "MOVE_ROCK_POLISH",
            "11": "MOVE_ROCK_THROW",
            "15": "MOVE_MAGNITUDE",
            "18": "MOVE_SELFDESTRUCT",
            "22": "MOVE_ROLLOUT",
            "27": "MOVE_ROCK_BLAST",
            "33": "MOVE_EARTHQUAKE",
            "38": "MOVE_EXPLOSION",
            "44": "MOVE_DOUBLE_EDGE",
            "49": "MOVE_STONE_EDGE"
        },
        "tutor": [
            "MOVE_MUD_SLAP",
            "MOVE_ROLLOUT",
            "MOVE_THUNDER_PUNCH",
            "MOVE_FIRE_PUNCH",
            "MOVE_SUPERPOWER",
            "MOVE_SNORE",
            "MOVE_ANCIENT_POWER",
            "MOVE_EARTH_POWER",
            "MOVE_SUCKER_PUNCH"
        ]
    },
    "evolutions": [
        [
            "EVO_TRADE",
            "SPECIES_GOLEM"
        ]
    ],
    "footprint": {
        "has_footprint": true,
        "footprint_size": "FOOTPRINT_MEDIUM"
    },
    "pokedex_data": {
        "height": 10,
        "weight": 1050,
        "body_shape": "SHAPE_BIPEDAL_TAILLESS",
        "trainer_scale_f": 272,
        "pokemon_scale_f": 256,
        "trainer_scale_m": 256,
        "pokemon_scale_m": 256,
        "trainer_pos_f": 8,
        "pokemon_pos_f": 10,
        "trainer_pos_m": 9,
        "pokemon_pos_m": 10,
        "entry_text": "It rolls on mountain paths to move.\\nOnce it builds momentum, no Pok\u00e9mon\\ncan stop it without difficulty.",
        "category": "Rock Pok\u00e9mon"
    }
}