{
    "name": "Brandon",
    "class": "TRAINER_CLASS_BUG_CATCHER",
    "items": [],
    "ai_flags": [
        "AI_FLAG_BASIC"
    ],
    "double_battle": false,
    "party": [
        {
            "species": "SPECIES_DUSTOX",
            "form": 0,
            "level": 30,
            "item": null,
            "moves": null,
            "power": 0,
            "ball_seal": 0
        },
        {
            "species": "SPECIES_KRICKETUNE",
            "form": 0,
            "level": 32,
            "item": null,
            "moves": null,
            "power": 0,
            "ball_seal": 0
        },
        {
            "species": "SPECIES_SCYTHER",
            "form": 0,
            "level": 34,
            "item": null,
            "moves": null,
            "power": 0,
            "ball_seal": 0
        }
    ]
}