{
    "land_rate": 10,
    "land_encounters": [
        {
            "level": 37,
            "species": "SPECIES_BRONZONG"
        },
        {
            "level": 38,
            "species": "SPECIES_GRAVELER"
        },
        {
            "level": 37,
            "species": "SPECIES_MEDICHAM"
        },
        {
            "level": 36,
            "species": "SPECIES_CLEFAIRY"
        },
        {
            "level": 39,
            "species": "SPECIES_MACHOKE"
        },
        {
            "level": 39,
            "species": "SPECIES_MEDICHAM"
        },
        {
            "level": 36,
            "species": "SPECIES_CHINGLING"
        },
        {
            "level": 37,
            "species": "SPECIES_NOSEPASS"
        },
        {
            "level": 38,
            "species": "SPECIES_GOLBAT"
        },
        {
            "level": 38,
            "species": "SPECIES_CHINGLING"
        },
        {
            "level": 38,
            "species": "SPECIES_GOLBAT"
        },
        {
            "level": 38,
            "species": "SPECIES_CHINGLING"
        }
    ],
    "swarms": [
        "SPECIES_BRONZONG",
        "SPECIES_GRAVELER"
    ],
    "morning": [
        "SPECIES_MEDICHAM",
        "SPECIES_GRAVELER"
    ],
    "night": [
        "SPECIES_GOLBAT",
        "SPECIES_CLEFAIRY"
    ],
    "radar": [
        "SPECIES_MACHOKE",
        "SPECIES_MEDICHAM",
        "SPECIES_GOLBAT",
        "SPECIES_CHINGLING"
    ],
    "rate_form0": 0,
    "rate_form1": 0,
    "rate_form2": 0,
    "rate_form3": 0,
    "rate_form4": 0,
    "unown_table": 0,
    "ruby": [
        "SPECIES_SOLROCK",
        "SPECIES_SOLROCK"
    ],
    "sapphire": [
        "SPECIES_LUNATONE",
        "SPECIES_LUNATONE"
    ],
    "emerald": [
        "SPECIES_GOLBAT",
        "SPECIES_CHINGLING"
    ],
    "firered": [
        "SPECIES_GOLBAT",
        "SPECIES_CHINGLING"
    ],
    "leafgreen": [
        "SPECIES_GOLBAT",
        "SPECIES_CHINGLING"
    ],
    "surf_rate": 10,
    "surf_encounters": [
        {
            "level_max": 30,
            "level_min": 20,
            "species": "SPECIES_ZUBAT"
        },
        {
            "level_max": 30,
            "level_min": 20,
            "species": "SPECIES_ZUBAT"
        },
        {
            "level_max": 40,
            "level_min": 20,
            "species": "SPECIES_GOLBAT"
        },
        {
            "level_max": 40,
            "level_min": 20,
            "species": "SPECIES_GOLBAT"
        },
        {
            "level_max": 40,
            "level_min": 20,
            "species": "SPECIES_GOLBAT"
        }
    ],
    "old_rod_rate": 25,
    "old_rod_encounters": [
        {
            "level_max": 6,
            "level_min": 4,
            "species": "SPECIES_MAGIKARP"
        },
        {
            "level_max": 7,
            "level_min": 3,
            "species": "SPECIES_MAGIKARP"
        },
        {
            "level_max": 10,
            "level_min": 5,
            "species": "SPECIES_MAGIKARP"
        },
        {
            "level_max": 10,
            "level_min": 5,
            "species": "SPECIES_MAGIKARP"
        },
        {
            "level_max": 15,
            "level_min": 5,
            "species": "SPECIES_MAGIKARP"
        }
    ],
    "good_rod_rate": 50,
    "good_rod_encounters": [
        {
            "level_max": 20,
            "level_min": 15,
            "species": "SPECIES_MAGIKARP"
        },
        {
            "level_max": 20,
            "level_min": 15,
            "species": "SPECIES_BARBOACH"
        },
        {
            "level_max": 25,
            "level_min": 10,
            "species": "SPECIES_MAGIKARP"
        },
        {
            "level_max": 25,
            "level_min": 10,
            "species": "SPECIES_BARBOACH"
        },
        {
            "level_max": 25,
            "level_min": 10,
            "species": "SPECIES_BARBOACH"
        }
    ],
    "super_rod_rate": 75,
    "super_rod_encounters": [
        {
            "level_max": 55,
            "level_min": 30,
            "species": "SPECIES_GYARADOS"
        },
        {
            "level_max": 25,
            "level_min": 15,
            "species": "SPECIES_DRATINI"
        },
        {
            "level_max": 50,
            "level_min": 20,
            "species": "SPECIES_WHISCASH"
        },
        {
            "level_max": 40,
            "level_min": 20,
            "species": "SPECIES_DRAGONAIR"
        },
        {
            "level_max": 55,
            "level_min": 35,
            "species": "SPECIES_DRAGONAIR"
        }
    ]
}
