{
    "bg_events": [
        {
            "script": 8136,
            "type": 2,
            "x": 741,
            "z": 264,
            "y": 0,
            "player_facing_dir": "BG_EVENT_DIR_ALL"
        },
        {
            "script": 8137,
            "type": 2,
            "x": 749,
            "z": 280,
            "y": 0,
            "player_facing_dir": "BG_EVENT_DIR_ALL"
        },
        {
            "script": 8159,
            "type": 2,
            "x": 744,
            "z": 326,
            "y": 0,
            "player_facing_dir": "BG_EVENT_DIR_ALL"
        }
    ],
    "object_events": [
        {
            "id": "ROUTE_227_ARROW_SIGNPOST_0",
            "graphics_id": "OBJ_EVENT_GFX_ARROW_SIGNPOST",
            "movement_type": "MOVEMENT_TYPE_NONE",
            "trainer_type": "TRAINER_TYPE_NONE",
            "hidden_flag": "0",
            "script": 2,
            "initial_dir": 0,
            "data": [
                3
            ],
            "movement_range_x": 0,
            "movement_range_z": 0,
            "x": 755,
            "z": 314,
            "y": 0
        },
        {
            "id": "LOCALID_ITEM_CHARCOAL",
            "graphics_id": "OBJ_EVENT_GFX_POKEBALL",
            "movement_type": "MOVEMENT_TYPE_NONE",
            "trainer_type": "TRAINER_TYPE_NONE",
            "hidden_flag": "FLAG_OBTAINED_ROUTE_227_CHARCOAL",
            "script": 7208,
            "initial_dir": 0,
            "data": [],
            "movement_range_x": 0,
            "movement_range_z": 0,
            "x": 759,
            "z": 283,
            "y": 0
        },
        {
            "id": "LOCALID_ITEM_ZINC",
            "graphics_id": "OBJ_EVENT_GFX_POKEBALL",
            "movement_type": "MOVEMENT_TYPE_NONE",
            "trainer_type": "TRAINER_TYPE_NONE",
            "hidden_flag": "FLAG_OBTAINED_ROUTE_227_ZINC",
            "script": 7209,
            "initial_dir": 0,
            "data": [],
            "movement_range_x": 0,
            "movement_range_z": 0,
            "x": 745,
            "z": 295,
            "y": 0
        },
        {
            "id": "ROUTE_227_RIVAL_3",
            "graphics_id": "OBJ_EVENT_GFX_BARRY",
            "movement_type": "MOVEMENT_TYPE_LOOK_WEST",
            "trainer_type": "TRAINER_TYPE_NONE",
            "hidden_flag": "FLAG_UNK_0x01D7",
            "script": 0,
            "initial_dir": 2,
            "data": [],
            "movement_range_x": 0,
            "movement_range_z": 0,
            "x": 739,
            "z": 305,
            "y": 0
        },
        {
            "id": "ROUTE_227_CRASHER_WAKE_4",
            "graphics_id": "OBJ_EVENT_GFX_CRASHER_WAKE",
            "movement_type": "MOVEMENT_TYPE_LOOK_EAST",
            "trainer_type": "TRAINER_TYPE_NONE",
            "hidden_flag": "FLAG_UNK_0x01D8",
            "script": 0,
            "initial_dir": 3,
            "data": [],
            "movement_range_x": 0,
            "movement_range_z": 0,
            "x": 738,
            "z": 305,
            "y": 0
        },
        {
            "id": "ROUTE_227_ACE_TRAINER_SAUL",
            "graphics_id": "OBJ_EVENT_GFX_ACE_TRAINER_M",
            "movement_type": "MOVEMENT_TYPE_LOOK_WEST",
            "trainer_type": "TRAINER_TYPE_NORMAL",
            "hidden_flag": "0",
            "script": "TRAINER_ACE_TRAINER_SAUL",
            "initial_dir": 2,
            "data": [
                2
            ],
            "movement_range_x": 0,
            "movement_range_z": 0,
            "x": 756,
            "z": 308,
            "y": 0
        },
        {
            "id": "ROUTE_227_RANGER_FELICIA",
            "graphics_id": "OBJ_EVENT_GFX_ACE_TRAINER_F",
            "movement_type": "MOVEMENT_TYPE_LOOK_NORTH",
            "trainer_type": "TRAINER_TYPE_NORMAL",
            "hidden_flag": "0",
            "script": "TRAINER_RANGER_FELICIA",
            "initial_dir": 0,
            "data": [
                2
            ],
            "movement_range_x": 0,
            "movement_range_z": 0,
            "x": 747,
            "z": 311,
            "y": 0
        },
        {
            "id": "ROUTE_227_BLACK_BELT_GRIFFIN",
            "graphics_id": "OBJ_EVENT_GFX_BLACK_BELT",
            "movement_type": "MOVEMENT_TYPE_LOOK_SOUTH_AND_EAST",
            "trainer_type": "TRAINER_TYPE_NORMAL",
            "hidden_flag": "0",
            "script": "TRAINER_BLACK_BELT_GRIFFIN",
            "initial_dir": 1,
            "data": [
                2
            ],
            "movement_range_x": 0,
            "movement_range_z": 0,
            "x": 764,
            "z": 266,
            "y": 0
        },
        {
            "id": "ROUTE_227_ACE_TRAINER_MIKAYLA",
            "graphics_id": "OBJ_EVENT_GFX_ACE_TRAINER_F",
            "movement_type": "MOVEMENT_TYPE_LOOK_WEST",
            "trainer_type": "TRAINER_TYPE_NORMAL",
            "hidden_flag": "0",
            "script": "TRAINER_ACE_TRAINER_MIKAYLA",
            "initial_dir": 2,
            "data": [
                2
            ],
            "movement_range_x": 0,
            "movement_range_z": 0,
            "x": 752,
            "z": 295,
            "y": 0
        },
        {
            "id": "ROUTE_227_VENT_9",
            "graphics_id": "OBJ_EVENT_GFX_VENT",
            "movement_type": "MOVEMENT_TYPE_NONE",
            "trainer_type": "TRAINER_TYPE_NONE",
            "hidden_flag": "0",
            "script": 2027,
            "initial_dir": 0,
            "data": [],
            "movement_range_x": 0,
            "movement_range_z": 0,
            "x": 754,
            "z": 297,
            "y": 0
        },
        {
            "id": "ROUTE_227_VENT_10",
            "graphics_id": "OBJ_EVENT_GFX_VENT",
            "movement_type": "MOVEMENT_TYPE_NONE",
            "trainer_type": "TRAINER_TYPE_NONE",
            "hidden_flag": "0",
            "script": 2027,
            "initial_dir": 0,
            "data": [],
            "movement_range_x": 0,
            "movement_range_z": 0,
            "x": 754,
            "z": 296,
            "y": 0
        },
        {
            "id": "ROUTE_227_BUCK_11",
            "graphics_id": "OBJ_EVENT_GFX_BUCK",
            "movement_type": "MOVEMENT_TYPE_LOOK_NORTH_AND_WEST",
            "trainer_type": "TRAINER_TYPE_NONE",
            "hidden_flag": "FLAG_UNK_0x028E",
            "script": 4,
            "initial_dir": 0,
            "data": [],
            "movement_range_x": 0,
            "movement_range_z": 0,
            "x": 758,
            "z": 275,
            "y": 0
        },
        {
            "id": "LOCALID_ITEM_YELLOW_SHARD",
            "graphics_id": "OBJ_EVENT_GFX_POKEBALL",
            "movement_type": "MOVEMENT_TYPE_NONE",
            "trainer_type": "TRAINER_TYPE_NONE",
            "hidden_flag": "FLAG_OBTAINED_ROUTE_227_YELLOW_SHARD",
            "script": 7307,
            "initial_dir": 0,
            "data": [],
            "movement_range_x": 0,
            "movement_range_z": 0,
            "x": 751,
            "z": 271,
            "y": 0
        }
    ],
    "warp_events": [
        {
            "x": 740,
            "z": 302,
            "dest_header_id": "MAP_HEADER_ROUTE_227_HOUSE",
            "dest_warp_id": 0
        }
    ],
    "coord_events": [
        {
            "script": 1,
            "x": 738,
            "z": 306,
            "y": 0,
            "width": 2,
            "length": 1,
            "var": "VAR_UNK_0x408B",
            "value": 0
        },
        {
            "script": 3,
            "x": 758,
            "z": 277,
            "y": 0,
            "width": 1,
            "length": 1,
            "var": "VAR_UNK_0x4119",
            "value": 0
        }
    ]
}
