{
    "bg_events": [
        {
            "script": 8147,
            "type": 2,
            "x": 718,
            "z": 419,
            "y": 0,
            "player_facing_dir": "BG_EVENT_DIR_ALL"
        },
        {
            "script": 8148,
            "type": 2,
            "x": 725,
            "z": 427,
            "y": 0,
            "player_facing_dir": "BG_EVENT_DIR_ALL"
        }
    ],
    "object_events": [
        {
            "graphics_id": "OBJ_EVENT_GFX_ROCK_SMASH",
            "movement_type": "MOVEMENT_TYPE_NONE",
            "trainer_type": "TRAINER_TYPE_NONE",
            "flag": "FLAG_UNK_0x0020",
            "script": 10001,
            "initial_dir": 0,
            "data": [],
            "movement_range_x": 0,
            "movement_range_z": 0,
            "x": 710,
            "z": 425,
            "y": 0
        },
        {
            "graphics_id": "OBJ_EVENT_GFX_ROCK_SMASH",
            "movement_type": "MOVEMENT_TYPE_NONE",
            "trainer_type": "TRAINER_TYPE_NONE",
            "flag": "FLAG_UNK_0x0021",
            "script": 10001,
            "initial_dir": 0,
            "data": [],
            "movement_range_x": 0,
            "movement_range_z": 0,
            "x": 716,
            "z": 419,
            "y": 0
        },
        {
            "graphics_id": "OBJ_EVENT_GFX_ROCK_SMASH",
            "movement_type": "MOVEMENT_TYPE_NONE",
            "trainer_type": "TRAINER_TYPE_NONE",
            "flag": "FLAG_UNK_0x0022",
            "script": 10001,
            "initial_dir": 0,
            "data": [],
            "movement_range_x": 0,
            "movement_range_z": 0,
            "x": 725,
            "z": 428,
            "y": 0
        },
        {
            "graphics_id": "OBJ_EVENT_GFX_ROCK_SMASH",
            "movement_type": "MOVEMENT_TYPE_NONE",
            "trainer_type": "TRAINER_TYPE_NONE",
            "flag": "FLAG_UNK_0x0023",
            "script": 10001,
            "initial_dir": 0,
            "data": [],
            "movement_range_x": 0,
            "movement_range_z": 0,
            "x": 729,
            "z": 431,
            "y": 0
        },
        {
            "graphics_id": "OBJ_EVENT_GFX_POKEBALL",
            "movement_type": "MOVEMENT_TYPE_NONE",
            "trainer_type": "TRAINER_TYPE_NONE",
            "flag": "FLAG_UNK_0x04DF",
            "script": 7233,
            "initial_dir": 0,
            "data": [],
            "movement_range_x": 0,
            "movement_range_z": 0,
            "x": 727,
            "z": 427,
            "y": 0
        },
        {
            "graphics_id": "OBJ_EVENT_GFX_UNK_100",
            "movement_type": "MOVEMENT_TYPE_BERRY_SOIL",
            "trainer_type": "TRAINER_TYPE_NONE",
            "flag": "0",
            "script": 2800,
            "initial_dir": 0,
            "data": [
                114
            ],
            "movement_range_x": 0,
            "movement_range_z": 0,
            "x": 684,
            "z": 420,
            "y": 0
        },
        {
            "graphics_id": "OBJ_EVENT_GFX_UNK_100",
            "movement_type": "MOVEMENT_TYPE_BERRY_SOIL",
            "trainer_type": "TRAINER_TYPE_NONE",
            "flag": "0",
            "script": 2800,
            "initial_dir": 0,
            "data": [
                115
            ],
            "movement_range_x": 0,
            "movement_range_z": 0,
            "x": 685,
            "z": 420,
            "y": 0
        },
        {
            "graphics_id": "OBJ_EVENT_GFX_UNK_100",
            "movement_type": "MOVEMENT_TYPE_BERRY_SOIL",
            "trainer_type": "TRAINER_TYPE_NONE",
            "flag": "0",
            "script": 2800,
            "initial_dir": 0,
            "data": [
                116
            ],
            "movement_range_x": 0,
            "movement_range_z": 0,
            "x": 686,
            "z": 420,
            "y": 0
        },
        {
            "graphics_id": "OBJ_EVENT_GFX_UNK_100",
            "movement_type": "MOVEMENT_TYPE_BERRY_SOIL",
            "trainer_type": "TRAINER_TYPE_NONE",
            "flag": "0",
            "script": 2800,
            "initial_dir": 0,
            "data": [
                117
            ],
            "movement_range_x": 0,
            "movement_range_z": 0,
            "x": 687,
            "z": 420,
            "y": 0
        },
        {
            "graphics_id": "OBJ_EVENT_GFX_SWIMMER_M",
            "movement_type": "MOVEMENT_TYPE_WALK_SOUTH_WEST_NORTH_EAST",
            "trainer_type": "TRAINER_TYPE_NORMAL",
            "flag": "0",
            "script": 3596,
            "initial_dir": 1,
            "data": [
                3
            ],
            "movement_range_x": 10,
            "movement_range_z": 2,
            "x": 731,
            "z": 440,
            "y": 0
        },
        {
            "graphics_id": "OBJ_EVENT_GFX_SWIMMER_F",
            "movement_type": "MOVEMENT_TYPE_WALK_EAST_SOUTH_NORTH_WEST",
            "trainer_type": "TRAINER_TYPE_NORMAL",
            "flag": "0",
            "script": 3600,
            "initial_dir": 3,
            "data": [
                3
            ],
            "movement_range_x": 13,
            "movement_range_z": 6,
            "x": 734,
            "z": 433,
            "y": 0
        },
        {
            "graphics_id": "OBJ_EVENT_GFX_SWIMMER_M",
            "movement_type": "MOVEMENT_TYPE_WALK_EAST_SOUTH_WEST_NORTH",
            "trainer_type": "TRAINER_TYPE_NORMAL",
            "flag": "0",
            "script": 3597,
            "initial_dir": 3,
            "data": [
                4
            ],
            "movement_range_x": 1,
            "movement_range_z": 8,
            "x": 750,
            "z": 430,
            "y": 0
        },
        {
            "graphics_id": "OBJ_EVENT_GFX_SWIMMER_F",
            "movement_type": "MOVEMENT_TYPE_WANDER_NORTH_AND_SOUTH",
            "trainer_type": "TRAINER_TYPE_NORMAL",
            "flag": "0",
            "script": 3601,
            "initial_dir": 0,
            "data": [
                4
            ],
            "movement_range_x": 0,
            "movement_range_z": 0,
            "x": 699,
            "z": 438,
            "y": 0
        },
        {
            "graphics_id": "OBJ_EVENT_GFX_SWIMMER_M",
            "movement_type": "MOVEMENT_TYPE_LOOK_SOUTH",
            "trainer_type": "TRAINER_TYPE_NORMAL",
            "flag": "0",
            "script": 3598,
            "initial_dir": 1,
            "data": [
                4
            ],
            "movement_range_x": 0,
            "movement_range_z": 0,
            "x": 699,
            "z": 433,
            "y": 0
        },
        {
            "graphics_id": "OBJ_EVENT_GFX_SWIMMER_F",
            "movement_type": "MOVEMENT_TYPE_WALK_BACK_AND_FORTH",
            "trainer_type": "TRAINER_TYPE_FACE_CLOCKWISE",
            "flag": "0",
            "script": 3602,
            "initial_dir": 3,
            "data": [
                3,
                3
            ],
            "movement_range_x": 3,
            "movement_range_z": 0,
            "x": 738,
            "z": 425,
            "y": 0
        },
        {
            "graphics_id": "OBJ_EVENT_GFX_ARROW_SIGNPOST",
            "movement_type": "MOVEMENT_TYPE_NONE",
            "trainer_type": "TRAINER_TYPE_NONE",
            "flag": "0",
            "script": 1,
            "initial_dir": 0,
            "data": [
                2
            ],
            "movement_range_x": 0,
            "movement_range_z": 0,
            "x": 680,
            "z": 429,
            "y": 0
        },
        {
            "graphics_id": "OBJ_EVENT_GFX_FISHERMAN",
            "movement_type": "MOVEMENT_TYPE_NONE",
            "trainer_type": "TRAINER_TYPE_NONE",
            "flag": "FLAG_UNK_0x0294",
            "script": 2,
            "initial_dir": 2,
            "data": [],
            "movement_range_x": 0,
            "movement_range_z": 0,
            "x": 682,
            "z": 430,
            "y": 0
        },
        {
            "graphics_id": "OBJ_EVENT_GFX_RICH_BOY",
            "movement_type": "MOVEMENT_TYPE_NONE",
            "trainer_type": "TRAINER_TYPE_NONE",
            "flag": "FLAG_UNK_0x0294",
            "script": 3,
            "initial_dir": 2,
            "data": [],
            "movement_range_x": 0,
            "movement_range_z": 0,
            "x": 682,
            "z": 431,
            "y": 0
        },
        {
            "graphics_id": "OBJ_EVENT_GFX_POKEBALL",
            "movement_type": "MOVEMENT_TYPE_NONE",
            "trainer_type": "TRAINER_TYPE_NONE",
            "flag": "FLAG_UNK_0x052B",
            "script": 7308,
            "initial_dir": 0,
            "data": [],
            "movement_range_x": 0,
            "movement_range_z": 0,
            "x": 708,
            "z": 431,
            "y": 0
        }
    ],
    "warp_events": [],
    "coord_events": []
}
