{
    "bg_events": [],
    "object_events": [
        {
            "graphics_id": "OBJ_EVENT_GFX_HIKER",
            "movement_type": "MOVEMENT_TYPE_NONE",
            "trainer_type": "TRAINER_TYPE_NONE",
            "flag": 0,
            "script": 3,
            "initial_dir": 1,
            "data": [],
            "movement_range_x": 0,
            "movement_range_z": 0,
            "x": 311,
            "z": 358,
            "y": 0
        },
        {
            "graphics_id": "OBJ_EVENT_GFX_HIKER",
            "movement_type": "MOVEMENT_TYPE_NONE",
            "trainer_type": "TRAINER_TYPE_NONE",
            "flag": 0,
            "script": 4,
            "initial_dir": 1,
            "data": [],
            "movement_range_x": 0,
            "movement_range_z": 0,
            "x": 392,
            "z": 121,
            "y": 0
        },
        {
            "graphics_id": "OBJ_EVENT_GFX_HIKER",
            "movement_type": "MOVEMENT_TYPE_NONE",
            "trainer_type": "TRAINER_TYPE_NONE",
            "flag": 0,
            "script": 4,
            "initial_dir": 1,
            "data": [],
            "movement_range_x": 0,
            "movement_range_z": 0,
            "x": 73,
            "z": 133,
            "y": 0
        },
        {
            "graphics_id": "OBJ_EVENT_GFX_HIKER",
            "movement_type": "MOVEMENT_TYPE_NONE",
            "trainer_type": "TRAINER_TYPE_NONE",
            "flag": 0,
            "script": 4,
            "initial_dir": 1,
            "data": [],
            "movement_range_x": 0,
            "movement_range_z": 0,
            "x": 343,
            "z": 151,
            "y": 0
        },
        {
            "graphics_id": "OBJ_EVENT_GFX_HIKER",
            "movement_type": "MOVEMENT_TYPE_NONE",
            "trainer_type": "TRAINER_TYPE_NONE",
            "flag": 0,
            "script": 4,
            "initial_dir": 1,
            "data": [],
            "movement_range_x": 0,
            "movement_range_z": 0,
            "x": 200,
            "z": 185,
            "y": 0
        },
        {
            "graphics_id": "OBJ_EVENT_GFX_HIKER",
            "movement_type": "MOVEMENT_TYPE_NONE",
            "trainer_type": "TRAINER_TYPE_NONE",
            "flag": 0,
            "script": 3,
            "initial_dir": 1,
            "data": [],
            "movement_range_x": 0,
            "movement_range_z": 0,
            "x": 167,
            "z": 392,
            "y": 0
        },
        {
            "graphics_id": "OBJ_EVENT_GFX_HIKER",
            "movement_type": "MOVEMENT_TYPE_NONE",
            "trainer_type": "TRAINER_TYPE_NONE",
            "flag": 0,
            "script": 3,
            "initial_dir": 1,
            "data": [],
            "movement_range_x": 0,
            "movement_range_z": 0,
            "x": 437,
            "z": 400,
            "y": 0
        },
        {
            "graphics_id": "OBJ_EVENT_GFX_HIKER",
            "movement_type": "MOVEMENT_TYPE_NONE",
            "trainer_type": "TRAINER_TYPE_NONE",
            "flag": 0,
            "script": 3,
            "initial_dir": 1,
            "data": [],
            "movement_range_x": 0,
            "movement_range_z": 0,
            "x": 119,
            "z": 422,
            "y": 0
        },
        {
            "graphics_id": "OBJ_EVENT_GFX_HIKER",
            "movement_type": "MOVEMENT_TYPE_NONE",
            "trainer_type": "TRAINER_TYPE_NONE",
            "flag": 0,
            "script": 4,
            "initial_dir": 1,
            "data": [],
            "movement_range_x": 0,
            "movement_range_z": 0,
            "x": 247,
            "z": 249,
            "y": 0
        },
        {
            "graphics_id": "OBJ_EVENT_GFX_HIKER",
            "movement_type": "MOVEMENT_TYPE_NONE",
            "trainer_type": "TRAINER_TYPE_NONE",
            "flag": 0,
            "script": 4,
            "initial_dir": 1,
            "data": [],
            "movement_range_x": 0,
            "movement_range_z": 0,
            "x": 151,
            "z": 264,
            "y": 0
        },
        {
            "graphics_id": "OBJ_EVENT_GFX_HIKER",
            "movement_type": "MOVEMENT_TYPE_NONE",
            "trainer_type": "TRAINER_TYPE_NONE",
            "flag": 0,
            "script": 4,
            "initial_dir": 1,
            "data": [],
            "movement_range_x": 0,
            "movement_range_z": 0,
            "x": 360,
            "z": 279,
            "y": 0
        },
        {
            "graphics_id": "OBJ_EVENT_GFX_HIKER",
            "movement_type": "MOVEMENT_TYPE_NONE",
            "trainer_type": "TRAINER_TYPE_NONE",
            "flag": 0,
            "script": 4,
            "initial_dir": 1,
            "data": [],
            "movement_range_x": 0,
            "movement_range_z": 0,
            "x": 264,
            "z": 294,
            "y": 0
        },
        {
            "graphics_id": "OBJ_EVENT_GFX_HIKER",
            "movement_type": "MOVEMENT_TYPE_NONE",
            "trainer_type": "TRAINER_TYPE_NONE",
            "flag": 0,
            "script": 3,
            "initial_dir": 1,
            "data": [],
            "movement_range_x": 0,
            "movement_range_z": 0,
            "x": 247,
            "z": 264,
            "y": 0
        },
        {
            "graphics_id": "OBJ_EVENT_GFX_HIKER",
            "movement_type": "MOVEMENT_TYPE_NONE",
            "trainer_type": "TRAINER_TYPE_NONE",
            "flag": 0,
            "script": 3,
            "initial_dir": 1,
            "data": [],
            "movement_range_x": 0,
            "movement_range_z": 0,
            "x": 279,
            "z": 456,
            "y": 0
        },
        {
            "graphics_id": "OBJ_EVENT_GFX_HIKER",
            "movement_type": "MOVEMENT_TYPE_NONE",
            "trainer_type": "TRAINER_TYPE_NONE",
            "flag": 0,
            "script": 3,
            "initial_dir": 1,
            "data": [],
            "movement_range_x": 0,
            "movement_range_z": 0,
            "x": 232,
            "z": 87,
            "y": 0
        },
        {
            "graphics_id": "OBJ_EVENT_GFX_HIKER",
            "movement_type": "MOVEMENT_TYPE_NONE",
            "trainer_type": "TRAINER_TYPE_NONE",
            "flag": 0,
            "script": 3,
            "initial_dir": 1,
            "data": [],
            "movement_range_x": 0,
            "movement_range_z": 0,
            "x": 264,
            "z": 279,
            "y": 0
        },
        {
            "graphics_id": "OBJ_EVENT_GFX_ROARK",
            "movement_type": "MOVEMENT_TYPE_LOOK_SOUTH",
            "trainer_type": "TRAINER_TYPE_NONE",
            "flag": 423,
            "script": 6,
            "initial_dir": 1,
            "data": [],
            "movement_range_x": 0,
            "movement_range_z": 0,
            "x": 1,
            "z": 1,
            "y": 0
        },
        {
            "graphics_id": "OBJ_EVENT_GFX_HIKER",
            "movement_type": "MOVEMENT_TYPE_NONE",
            "trainer_type": "TRAINER_TYPE_NONE",
            "flag": 0,
            "script": 5,
            "initial_dir": 1,
            "data": [],
            "movement_range_x": 0,
            "movement_range_z": 0,
            "x": 4,
            "z": 1,
            "y": 0
        },
        {
            "graphics_id": "OBJ_EVENT_GFX_HIKER",
            "movement_type": "MOVEMENT_TYPE_NONE",
            "trainer_type": "TRAINER_TYPE_NONE",
            "flag": 0,
            "script": 5,
            "initial_dir": 1,
            "data": [],
            "movement_range_x": 0,
            "movement_range_z": 0,
            "x": 4,
            "z": 2,
            "y": 0
        },
        {
            "graphics_id": "OBJ_EVENT_GFX_HIKER",
            "movement_type": "MOVEMENT_TYPE_NONE",
            "trainer_type": "TRAINER_TYPE_NONE",
            "flag": 0,
            "script": 5,
            "initial_dir": 1,
            "data": [],
            "movement_range_x": 0,
            "movement_range_z": 0,
            "x": 4,
            "z": 3,
            "y": 0
        },
        {
            "graphics_id": "OBJ_EVENT_GFX_HIKER",
            "movement_type": "MOVEMENT_TYPE_NONE",
            "trainer_type": "TRAINER_TYPE_NONE",
            "flag": 0,
            "script": 5,
            "initial_dir": 1,
            "data": [],
            "movement_range_x": 0,
            "movement_range_z": 0,
            "x": 4,
            "z": 4,
            "y": 0
        }
    ],
    "warp_events": [],
    "coord_events": []
}
